Project/uart_rx.v
module uart_rx #(parameter CLKS_PER_BIT = 16)
(
    input wire i_rx,
    input wire clk,
    output reg [7:0] data_out,
    output wire data_ready
);

localparam Idle = 0, start = 1, datarcv = 2, stop = 3;

reg [1:0] state = Idle;
reg [2:0] bit_index = 0;
reg [7:0] data_buffer = 0;
reg dataReady = 0;
reg [15:0] counter = 0;

reg rx_buffer = 1'b1;
reg rx = 1'b1;

assign data_ready = dataReady;

always @(posedge clk) begin
    rx_buffer <= i_rx;
    rx <= rx_buffer;
end

always @(posedge clk) begin
    case (state)
        Idle: begin
            data_buffer <= 0;
            dataReady <= 0;
            counter <= 0;
            bit_index <= 0;
            if (~rx)
                state <= start;
        end

        start: begin
            if (counter == (CLKS_PER_BIT - 1)/2) begin
                if (rx == 0) begin
                    counter <= 0;
                    state <= datarcv;
                end else begin
                    state <= Idle;
                end
            end else begin
                counter <= counter + 1;
            end
        end

        datarcv: begin 
            if (counter < CLKS_PER_BIT - 1) begin
                counter <= counter + 1;
            end else begin
                data_buffer[bit_index] <= rx;
                counter <= 0;
                if (bit_index == 7) begin 
                    state <= stop;
                end else begin  
                    bit_index <= bit_index + 1;
                end
            end
        end

        stop: begin 
            if (counter < CLKS_PER_BIT - 1) begin
                counter <= counter + 1;
            end else begin 
                dataReady <= 1;
                data_out <= data_buffer;
                counter <= 0;
                state <= Idle; 
            end
        end

        default: state <= Idle;
    endcase
end

endmodule

Project/uart_rx.vcd
$version Generated by VerilatedVcd $end
$date Thu Jun  5 12:07:18 2025
 $end
$timescale  10s $end

 $scope module TOP $end
  $var wire  1 + clk $end
  $var wire  8 , data_out [7:0] $end
  $var wire  1 - data_ready $end
  $var wire  1 * i_rx $end
  $scope module uart_rx $end
   $var wire 32 . CLKS_PER_BIT [31:0] $end
   $var wire 32 / Idle [31:0] $end
   $var wire  3 $ bit_index [2:0] $end
   $var wire  1 + clk $end
   $var wire 16 ' counter [15:0] $end
   $var wire  1 & dataReady $end
   $var wire  8 % data_buffer [7:0] $end
   $var wire  8 , data_out [7:0] $end
   $var wire  1 - data_ready $end
   $var wire 32 1 datarcv [31:0] $end
   $var wire  1 * i_rx $end
   $var wire  1 ) rx $end
   $var wire  1 ( rx_buffer $end
   $var wire 32 0 start [31:0] $end
   $var wire  2 # state [1:0] $end
   $var wire 32 2 stop [31:0] $end
  $upscope $end
 $upscope $end
$enddefinitions $end


#0
b00 #
b000 $
b00000000 %
0&
b0000000000000000 '
1(
1)
1*
0+
b00000000 ,
0-
b00000000000000000000000000010000 .
b00000000000000000000000000000000 /
b00000000000000000000000000000001 0
b00000000000000000000000000000010 1
b00000000000000000000000000000011 2
#1
1+
#2
0+
#3
1+
#4
0+
#5
1+
#6
0+
#7
1+
#8
0+
#9
1+
#10
0+
#11
1+
#12
0+
#13
1+
#14
0+
#15
1+
#16
0+
#17
1+
#18
0+
#19
1+
#20
0+
#21
1+
#22
0+
#23
1+
#24
0+
#25
1+
#26
0+
#27
1+
#28
0+
#29
1+
#30
0+
#31
1+
#32
0+
#33
1+
#34
0+
#35
1+
#36
0+
#37
1+
#38
0+
#39
1+
#40
0+
#41
1+
#42
0+
#43
1+
#44
0+
#45
1+
#46
0+
#47
1+
#48
0+
#49
1+
#50
0+
#51
1+
#52
0+
#53
1+
#54
0+
#55
1+
#56
0+
#57
1+
#58
0+
#59
1+
#60
0+
#61
1+
#62
0+
#63
1+
#64
0+
#65
1+
#66
0+
#67
1+
#68
0+
#69
1+
#70
0+
#71
1+
#72
0+
#73
1+
#74
0+
#75
1+
#76
0+
#77
1+
#78
0+
#79
1+
#80
0+
#81
1+
#82
0+
#83
1+
#84
0+
#85
1+
#86
0+
#87
1+
#88
0+
#89
1+
#90
0+
#91
1+
#92
0+
#93
1+
#94
0+
#95
1+
#96
0+
#97
1+
#98
0+
#99
1+
#100
0+
#101
1+
#102
0+
#103
1+
#104
0+
#105
1+
#106
0+
#107
1+
#108
0+
#109
1+
#110
0+
#111
1+
#112
0+
#113
1+
#114
0+
#115
1+
#116
0+
#117
1+
#118
0+
#119
1+
#120
0+
#121
1+
#122
0+
#123
1+
#124
0+
#125
1+
#126
0+
#127
1+
#128
0+
#129
1+
#130
0+
#131
1+
#132
0+
#133
1+
#134
0+
#135
1+
#136
0+
#137
1+
#138
0+
#139
1+
#140
0+
#141
1+
#142
0+
#143
1+
#144
0+
#145
1+
#146
0+
#147
1+
#148
0+
#149
1+
#150
0+
#151
1+
#152
0+
#153
1+
#154
0+
#155
1+
#156
0+
#157
1+
#158
0+
#159
1+
#160
0+
#161
1+
#162
0+
#163
1+
#164
0+
#165
1+
#166
0+
#167
1+
#168
0+
#169
1+
#170
0+
#171
1+
#172
0+
#173
1+
#174
0+
#175
1+
#176
0+
#177
1+
#178
0+
#179
1+
#180
0+
#181
1+
#182
0+
#183
1+
#184
0+
#185
1+
#186
0+
#187
1+
#188
0+
#189
1+
#190
0+
#191
1+
#192
0+
#193
1+
#194
0+
#195
1+
#196
0+
#197
1+
#198
0+
#199
1+
#200
0*
0+
#201
0(
1+
#202
0+
#203
0)
1+
#204
0+
#205
b01 #
1+
#206
0+
#207
b0000000000000001 '
1+
#208
0+
#209
b0000000000000010 '
1+
#210
0+
#211
b0000000000000011 '
1+
#212
0+
#213
b0000000000000100 '
1+
#214
0+
#215
b0000000000000101 '
1+
#216
0+
#217
b0000000000000110 '
1+
#218
0+
#219
b0000000000000111 '
1+
#220
0+
#221
b10 #
b0000000000000000 '
1+
#222
0+
#223
b0000000000000001 '
1+
#224
0+
#225
b0000000000000010 '
1+
#226
0+
#227
b0000000000000011 '
1+
#228
0+
#229
b0000000000000100 '
1+
#230
0+
#231
b0000000000000101 '
1+
#232
0+
#233
b0000000000000110 '
1+
#234
0+
#235
b0000000000000111 '
1+
#236
0+
#237
b0000000000001000 '
1+
#238
0+
#239
b0000000000001001 '
1+
#240
0+
#241
b0000000000001010 '
1+
#242
0+
#243
b0000000000001011 '
1+
#244
0+
#245
b0000000000001100 '
1+
#246
0+
#247
b0000000000001101 '
1+
#248
0+
#249
b0000000000001110 '
1+
#250
0+
#251
b0000000000001111 '
1+
#252
0+
#253
b001 $
b0000000000000000 '
1+
#254
0+
#255
b0000000000000001 '
1+
#256
0+
#257
b0000000000000010 '
1+
#258
0+
#259
b0000000000000011 '
1+
#260
0+
#261
b0000000000000100 '
1+
#262
0+
#263
b0000000000000101 '
1+
#264
0+
#265
b0000000000000110 '
1+
#266
0+
#267
b0000000000000111 '
1+
#268
0+
#269
b0000000000001000 '
1+
#270
0+
#271
b0000000000001001 '
1+
#272
0+
#273
b0000000000001010 '
1+
#274
0+
#275
b0000000000001011 '
1+
#276
0+
#277
b0000000000001100 '
1+
#278
0+
#279
b0000000000001101 '
1+
#280
0+
#281
b0000000000001110 '
1+
#282
0+
#283
b0000000000001111 '
1+
#284
0+
#285
b010 $
b0000000000000000 '
1+
#286
0+
#287
b0000000000000001 '
1+
#288
0+
#289
b0000000000000010 '
1+
#290
0+
#291
b0000000000000011 '
1+
#292
0+
#293
b0000000000000100 '
1+
#294
0+
#295
b0000000000000101 '
1+
#296
0+
#297
b0000000000000110 '
1+
#298
0+
#299
b0000000000000111 '
1+
#300
0+
#301
b0000000000001000 '
1+
#302
0+
#303
b0000000000001001 '
1+
#304
0+
#305
b0000000000001010 '
1+
#306
0+
#307
b0000000000001011 '
1+
#308
0+
#309
b0000000000001100 '
1+
#310
0+
#311
b0000000000001101 '
1+
#312
0+
#313
b0000000000001110 '
1+
#314
0+
#315
b0000000000001111 '
1+
#316
0+
#317
b011 $
b0000000000000000 '
1+
#318
0+
#319
b0000000000000001 '
1+
#320
0+
#321
b0000000000000010 '
1+
#322
0+
#323
b0000000000000011 '
1+
#324
0+
#325
b0000000000000100 '
1+
#326
0+
#327
b0000000000000101 '
1+
#328
0+
#329
b0000000000000110 '
1+
#330
0+
#331
b0000000000000111 '
1+
#332
0+
#333
b0000000000001000 '
1+
#334
0+
#335
b0000000000001001 '
1+
#336
0+
#337
b0000000000001010 '
1+
#338
0+
#339
b0000000000001011 '
1+
#340
0+
#341
b0000000000001100 '
1+
#342
0+
#343
b0000000000001101 '
1+
#344
0+
#345
b0000000000001110 '
1+
#346
0+
#347
b0000000000001111 '
1+
#348
0+
#349
b100 $
b0000000000000000 '
1+
#350
0+
#351
b0000000000000001 '
1+
#352
0+
#353
b0000000000000010 '
1+
#354
0+
#355
b0000000000000011 '
1+
#356
0+
#357
b0000000000000100 '
1+
#358
0+
#359
b0000000000000101 '
1+
#360
0+
#361
b0000000000000110 '
1+
#362
0+
#363
b0000000000000111 '
1+
#364
0+
#365
b0000000000001000 '
1+
#366
0+
#367
b0000000000001001 '
1+
#368
0+
#369
b0000000000001010 '
1+
#370
0+
#371
b0000000000001011 '
1+
#372
0+
#373
b0000000000001100 '
1+
#374
0+
#375
b0000000000001101 '
1+
#376
0+
#377
b0000000000001110 '
1+
#378
0+
#379
b0000000000001111 '
1+
#380
0+
#381
b101 $
b0000000000000000 '
1+
#382
0+
#383
b0000000000000001 '
1+
#384
0+
#385
b0000000000000010 '
1+
#386
0+
#387
b0000000000000011 '
1+
#388
0+
#389
b0000000000000100 '
1+
#390
0+
#391
b0000000000000101 '
1+
#392
0+
#393
b0000000000000110 '
1+
#394
0+
#395
b0000000000000111 '
1+
#396
0+
#397
b0000000000001000 '
1+
#398
0+
#399
b0000000000001001 '
1+
#400
0+
#401
b0000000000001010 '
1+
#402
0+
#403
b0000000000001011 '
1+
#404
0+
#405
b0000000000001100 '
1+
#406
0+
#407
b0000000000001101 '
1+
#408
0+
#409
b0000000000001110 '
1+
#410
0+
#411
b0000000000001111 '
1+
#412
0+
#413
b110 $
b0000000000000000 '
1+
#414
0+
#415
b0000000000000001 '
1+
#416
0+
#417
b0000000000000010 '
1+
#418
0+
#419
b0000000000000011 '
1+
#420
0+
#421
b0000000000000100 '
1+
#422
0+
#423
b0000000000000101 '
1+
#424
0+
#425
b0000000000000110 '
1+
#426
0+
#427
b0000000000000111 '
1+
#428
0+
#429
b0000000000001000 '
1+
#430
0+
#431
b0000000000001001 '
1+
#432
0+
#433
b0000000000001010 '
1+
#434
0+
#435
b0000000000001011 '
1+
#436
0+
#437
b0000000000001100 '
1+
#438
0+
#439
b0000000000001101 '
1+
#440
0+
#441
b0000000000001110 '
1+
#442
0+
#443
b0000000000001111 '
1+
#444
0+
#445
b111 $
b0000000000000000 '
1+
#446
0+
#447
b0000000000000001 '
1+
#448
0+
#449
b0000000000000010 '
1+
#450
0+
#451
b0000000000000011 '
1+
#452
0+
#453
b0000000000000100 '
1+
#454
0+
#455
b0000000000000101 '
1+
#456
0+
#457
b0000000000000110 '
1+
#458
0+
#459
b0000000000000111 '
1+
#460
0+
#461
b0000000000001000 '
1+
#462
0+
#463
b0000000000001001 '
1+
#464
0+
#465
b0000000000001010 '
1+
#466
0+
#467
b0000000000001011 '
1+
#468
0+
#469
b0000000000001100 '
1+
#470
0+
#471
b0000000000001101 '
1+
#472
0+
#473
b0000000000001110 '
1+
#474
0+
#475
b0000000000001111 '
1+
#476
0+
#477
b11 #
b0000000000000000 '
1+
#478
0+
#479
b0000000000000001 '
1+
#480
0+
#481
b0000000000000010 '
1+
#482
0+
#483
b0000000000000011 '
1+
#484
0+
#485
b0000000000000100 '
1+
#486
0+
#487
b0000000000000101 '
1+
#488
0+
#489
b0000000000000110 '
1+
#490
0+
#491
b0000000000000111 '
1+
#492
0+
#493
b0000000000001000 '
1+
#494
0+
#495
b0000000000001001 '
1+
#496
0+
#497
b0000000000001010 '
1+
#498
0+
#499
b0000000000001011 '
1+
#500
0+
#501
b0000000000001100 '
1+
#502
0+
#503
b0000000000001101 '
1+
#504
0+
#505
b0000000000001110 '
1+
#506
0+
#507
b0000000000001111 '
1+
#508
0+
#509
b00 #
1&
b0000000000000000 '
1+
1-
#510
0+
#511
b01 #
b000 $
0&
1+
0-
#512
0+
#513
b0000000000000001 '
1+
#514
0+
#515
b0000000000000010 '
1+
#516
0+
#517
b0000000000000011 '
1+
#518
0+
#519
b0000000000000100 '
1+
#520
0+
#521
b0000000000000101 '
1+
#522
0+
#523
b0000000000000110 '
1+
#524
0+
#525
b0000000000000111 '
1+
#526
0+
#527
b10 #
b0000000000000000 '
1+
#528
0+
#529
b0000000000000001 '
1+
#530
0+
#531
b0000000000000010 '
1+
#532
0+
#533
b0000000000000011 '
1+
#534
0+
#535
b0000000000000100 '
1+
#536
0+
#537
b0000000000000101 '
1+
#538
0+
#539
b0000000000000110 '
1+
#540
0+
#541
b0000000000000111 '
1+
#542
0+
#543
b0000000000001000 '
1+
#544
0+
#545
b0000000000001001 '
1+
#546
0+
#547
b0000000000001010 '
1+
#548
0+
#549
b0000000000001011 '
1+
#550
0+
#551
b0000000000001100 '
1+
#552
0+
#553
b0000000000001101 '
1+
#554
0+
#555
b0000000000001110 '
1+
#556
0+
#557
b0000000000001111 '
1+
#558
0+
#559
b001 $
b0000000000000000 '
1+
#560
0+
#561
b0000000000000001 '
1+
#562
0+
#563
b0000000000000010 '
1+
#564
0+
#565
b0000000000000011 '
1+
#566
0+
#567
b0000000000000100 '
1+
#568
0+
#569
b0000000000000101 '
1+
#570
0+
#571
b0000000000000110 '
1+
#572
0+
#573
b0000000000000111 '
1+
#574
0+
#575
b0000000000001000 '
1+
#576
0+
#577
b0000000000001001 '
1+
#578
0+
#579
b0000000000001010 '
1+
#580
0+
#581
b0000000000001011 '
1+
#582
0+
#583
b0000000000001100 '
1+
#584
0+
#585
b0000000000001101 '
1+
#586
0+
#587
b0000000000001110 '
1+
#588
0+
#589
b0000000000001111 '
1+
#590
0+
#591
b010 $
b0000000000000000 '
1+
#592
0+
#593
b0000000000000001 '
1+
#594
0+
#595
b0000000000000010 '
1+
#596
0+
#597
b0000000000000011 '
1+
#598
0+
#599
b0000000000000100 '
1+
#600
0+
#601
b0000000000000101 '
1+
#602
0+
#603
b0000000000000110 '
1+
#604
0+
#605
b0000000000000111 '
1+
#606
0+
#607
b0000000000001000 '
1+
#608
0+
#609
b0000000000001001 '
1+
#610
0+
#611
b0000000000001010 '
1+
#612
0+
#613
b0000000000001011 '
1+
#614
0+
#615
b0000000000001100 '
1+
#616
0+
#617
b0000000000001101 '
1+
#618
0+
#619
b0000000000001110 '
1+
#620
0+
#621
b0000000000001111 '
1+
#622
0+
#623
b011 $
b0000000000000000 '
1+
#624
0+
#625
b0000000000000001 '
1+
#626
0+
#627
b0000000000000010 '
1+
#628
0+
#629
b0000000000000011 '
1+
#630
0+
#631
b0000000000000100 '
1+
#632
0+
#633
b0000000000000101 '
1+
#634
0+
#635
b0000000000000110 '
1+
#636
0+
#637
b0000000000000111 '
1+
#638
0+
#639
b0000000000001000 '
1+
#640
0+
#641
b0000000000001001 '
1+
#642
0+
#643
b0000000000001010 '
1+
#644
0+
#645
b0000000000001011 '
1+
#646
0+
#647
b0000000000001100 '
1+
#648
0+
#649
b0000000000001101 '
1+
#650
0+
#651
b0000000000001110 '
1+
#652
0+
#653
b0000000000001111 '
1+
#654
0+
#655
b100 $
b0000000000000000 '
1+
#656
0+
#657
b0000000000000001 '
1+
#658
0+
#659
b0000000000000010 '
1+
#660
0+
#661
b0000000000000011 '
1+
#662
0+
#663
b0000000000000100 '
1+
#664
0+
#665
b0000000000000101 '
1+
#666
0+
#667
b0000000000000110 '
1+
#668
0+
#669
b0000000000000111 '
1+
#670
0+
#671
b0000000000001000 '
1+
#672
0+
#673
b0000000000001001 '
1+
#674
0+
#675
b0000000000001010 '
1+
#676
0+
#677
b0000000000001011 '
1+
#678
0+
#679
b0000000000001100 '
1+
#680
0+
#681
b0000000000001101 '
1+
#682
0+
#683
b0000000000001110 '
1+
#684
0+
#685
b0000000000001111 '
1+
#686
0+
#687
b101 $
b0000000000000000 '
1+
#688
0+
#689
b0000000000000001 '
1+
#690
0+
#691
b0000000000000010 '
1+
#692
0+
#693
b0000000000000011 '
1+
#694
0+
#695
b0000000000000100 '
1+
#696
0+
#697
b0000000000000101 '
1+
#698
0+
#699
b0000000000000110 '
1+
#700
0+
#701
b0000000000000111 '
1+
#702
0+
#703
b0000000000001000 '
1+
#704
0+
#705
b0000000000001001 '
1+
#706
0+
#707
b0000000000001010 '
1+
#708
0+
#709
b0000000000001011 '
1+
#710
0+
#711
b0000000000001100 '
1+
#712
0+
#713
b0000000000001101 '
1+
#714
0+
#715
b0000000000001110 '
1+
#716
0+
#717
b0000000000001111 '
1+
#718
0+
#719
b110 $
b0000000000000000 '
1+
#720
0+
#721
b0000000000000001 '
1+
#722
0+
#723
b0000000000000010 '
1+
#724
0+
#725
b0000000000000011 '
1+
#726
0+
#727
b0000000000000100 '
1+
#728
0+
#729
b0000000000000101 '
1+
#730
0+
#731
b0000000000000110 '
1+
#732
0+
#733
b0000000000000111 '
1+
#734
0+
#735
b0000000000001000 '
1+
#736
0+
#737
b0000000000001001 '
1+
#738
0+
#739
b0000000000001010 '
1+
#740
0+
#741
b0000000000001011 '
1+
#742
0+
#743
b0000000000001100 '
1+
#744
0+
#745
b0000000000001101 '
1+
#746
0+
#747
b0000000000001110 '
1+
#748
0+
#749
b0000000000001111 '
1+
#750
0+
#751
b111 $
b0000000000000000 '
1+
#752
0+
#753
b0000000000000001 '
1+
#754
0+
#755
b0000000000000010 '
1+
#756
0+
#757
b0000000000000011 '
1+
#758
0+
#759
b0000000000000100 '
1+
#760
0+
#761
b0000000000000101 '
1+
#762
0+
#763
b0000000000000110 '
1+
#764
0+
#765
b0000000000000111 '
1+
#766
0+
#767
b0000000000001000 '
1+
#768
0+
#769
b0000000000001001 '
1+
#770
0+
#771
b0000000000001010 '
1+
#772
0+
#773
b0000000000001011 '
1+
#774
0+
#775
b0000000000001100 '
1+
#776
0+
#777
b0000000000001101 '
1+
#778
0+
#779
b0000000000001110 '
1+
#780
0+
#781
b0000000000001111 '
1+
#782
0+
#783
b11 #
b0000000000000000 '
1+
#784
0+
#785
b0000000000000001 '
1+
#786
0+
#787
b0000000000000010 '
1+
#788
0+
#789
b0000000000000011 '
1+
#790
0+
#791
b0000000000000100 '
1+
#792
0+
#793
b0000000000000101 '
1+
#794
0+
#795
b0000000000000110 '
1+
#796
0+
#797
b0000000000000111 '
1+
#798
0+
#799
b0000000000001000 '
1+
#800
0+
#801
b0000000000001001 '
1+
#802
0+
#803
b0000000000001010 '
1+
#804
0+
#805
b0000000000001011 '
1+
#806
0+
#807
b0000000000001100 '
1+
#808
0+
#809
b0000000000001101 '
1+
#810
0+
#811
b0000000000001110 '
1+
#812
0+
#813
b0000000000001111 '
1+
#814
0+
#815
b00 #
1&
b0000000000000000 '
1+
1-
#816
0+
#817
b01 #
b000 $
0&
1+
0-
#818
0+
#819
b0000000000000001 '
1+
#820
0+
#821
b0000000000000010 '
1+
#822
0+
#823
b0000000000000011 '
1+
#824
0+
#825
b0000000000000100 '
1+
#826
0+
#827
b0000000000000101 '
1+
#828
0+
#829
b0000000000000110 '
1+
#830
0+
#831
b0000000000000111 '
1+
#832
0+
#833
b10 #
b0000000000000000 '
1+
#834
0+
#835
b0000000000000001 '
1+
#836
0+
#837
b0000000000000010 '
1+
#838
0+
#839
b0000000000000011 '
1+
#840
0+
#841
b0000000000000100 '
1+
#842
0+
#843
b0000000000000101 '
1+
#844
0+
#845
b0000000000000110 '
1+
#846
0+
#847
b0000000000000111 '
1+
#848
0+
#849
b0000000000001000 '
1+
#850
0+
#851
b0000000000001001 '
1+
#852
0+
#853
b0000000000001010 '
1+
#854
0+
#855
b0000000000001011 '
1+
#856
0+
#857
b0000000000001100 '
1+
#858
0+
#859
b0000000000001101 '
1+
#860
0+
#861
b0000000000001110 '
1+
#862
0+
#863
b0000000000001111 '
1+
#864
0+
#865
b001 $
b0000000000000000 '
1+
#866
0+
#867
b0000000000000001 '
1+
#868
0+
#869
b0000000000000010 '
1+
#870
0+
#871
b0000000000000011 '
1+
#872
0+
#873
b0000000000000100 '
1+
#874
0+
#875
b0000000000000101 '
1+
#876
0+
#877
b0000000000000110 '
1+
#878
0+
#879
b0000000000000111 '
1+
#880
0+
#881
b0000000000001000 '
1+
#882
0+
#883
b0000000000001001 '
1+
#884
0+
#885
b0000000000001010 '
1+
#886
0+
#887
b0000000000001011 '
1+
#888
0+
#889
b0000000000001100 '
1+
#890
0+
#891
b0000000000001101 '
1+
#892
0+
#893
b0000000000001110 '
1+
#894
0+
#895
b0000000000001111 '
1+
#896
0+
#897
b010 $
b0000000000000000 '
1+
#898
0+
#899
b0000000000000001 '
1+
#900
0+
#901
b0000000000000010 '
1+
#902
0+
#903
b0000000000000011 '
1+
#904
0+
#905
b0000000000000100 '
1+
#906
0+
#907
b0000000000000101 '
1+
#908
0+
#909
b0000000000000110 '
1+
#910
0+
#911
b0000000000000111 '
1+
#912
0+
#913
b0000000000001000 '
1+
#914
0+
#915
b0000000000001001 '
1+
#916
0+
#917
b0000000000001010 '
1+
#918
0+
#919
b0000000000001011 '
1+
#920
0+
#921
b0000000000001100 '
1+
#922
0+
#923
b0000000000001101 '
1+
#924
0+
#925
b0000000000001110 '
1+
#926
0+
#927
b0000000000001111 '
1+
#928
0+
#929
b011 $
b0000000000000000 '
1+
#930
0+
#931
b0000000000000001 '
1+
#932
0+
#933
b0000000000000010 '
1+
#934
0+
#935
b0000000000000011 '
1+
#936
0+
#937
b0000000000000100 '
1+
#938
0+
#939
b0000000000000101 '
1+
#940
0+
#941
b0000000000000110 '
1+
#942
0+
#943
b0000000000000111 '
1+
#944
0+
#945
b0000000000001000 '
1+
#946
0+
#947
b0000000000001001 '
1+
#948
0+
#949
b0000000000001010 '
1+
#950
0+
#951
b0000000000001011 '
1+
#952
0+
#953
b0000000000001100 '
1+
#954
0+
#955
b0000000000001101 '
1+
#956
0+
#957
b0000000000001110 '
1+
#958
0+
#959
b0000000000001111 '
1+
#960
0+
#961
b100 $
b0000000000000000 '
1+
#962
0+
#963
b0000000000000001 '
1+
#964
0+
#965
b0000000000000010 '
1+
#966
0+
#967
b0000000000000011 '
1+
#968
0+
#969
b0000000000000100 '
1+
#970
0+
#971
b0000000000000101 '
1+
#972
0+
#973
b0000000000000110 '
1+
#974
0+
#975
b0000000000000111 '
1+
#976
0+
#977
b0000000000001000 '
1+
#978
0+
#979
b0000000000001001 '
1+
#980
0+
#981
b0000000000001010 '
1+
#982
0+
#983
b0000000000001011 '
1+
#984
0+
#985
b0000000000001100 '
1+
#986
0+
#987
b0000000000001101 '
1+
#988
0+
#989
b0000000000001110 '
1+
#990
0+
#991
b0000000000001111 '
1+
#992
0+
#993
b101 $
b0000000000000000 '
1+
#994
0+
#995
b0000000000000001 '
1+
#996
0+
#997
b0000000000000010 '
1+
#998
0+
#999
b0000000000000011 '
1+
#1000
0+
#1001
b0000000000000100 '
1+
#1002
0+
#1003
b0000000000000101 '
1+
#1004
0+
#1005
b0000000000000110 '
1+
#1006
0+
#1007
b0000000000000111 '
1+
#1008
0+
#1009
b0000000000001000 '
1+
#1010
0+
#1011
b0000000000001001 '
1+
#1012
0+
#1013
b0000000000001010 '
1+
#1014
0+
#1015
b0000000000001011 '
1+
#1016
0+
#1017
b0000000000001100 '
1+
#1018
0+
#1019
b0000000000001101 '
1+
#1020
0+
#1021
b0000000000001110 '
1+
#1022
0+
#1023
b0000000000001111 '
1+
#1024
0+
#1025
b110 $
b0000000000000000 '
1+
#1026
0+
#1027
b0000000000000001 '
1+
#1028
0+
#1029
b0000000000000010 '
1+
#1030
0+
#1031
b0000000000000011 '
1+
#1032
0+
#1033
b0000000000000100 '
1+
#1034
0+
#1035
b0000000000000101 '
1+
#1036
0+
#1037
b0000000000000110 '
1+
#1038
0+
#1039
b0000000000000111 '
1+
#1040
0+
#1041
b0000000000001000 '
1+
#1042
0+
#1043
b0000000000001001 '
1+
#1044
0+
#1045
b0000000000001010 '
1+
#1046
0+
#1047
b0000000000001011 '
1+
#1048
0+
#1049
b0000000000001100 '
1+
#1050
0+
#1051
b0000000000001101 '
1+
#1052
0+
#1053
b0000000000001110 '
1+
#1054
0+
#1055
b0000000000001111 '
1+
#1056
0+
#1057
b111 $
b0000000000000000 '
1+
#1058
0+
#1059
b0000000000000001 '
1+
#1060
0+
#1061
b0000000000000010 '
1+
#1062
0+
#1063
b0000000000000011 '
1+
#1064
0+
#1065
b0000000000000100 '
1+
#1066
0+
#1067
b0000000000000101 '
1+
#1068
0+
#1069
b0000000000000110 '
1+
#1070
0+
#1071
b0000000000000111 '
1+
#1072
0+
#1073
b0000000000001000 '
1+
#1074
0+
#1075
b0000000000001001 '
1+
#1076
0+
#1077
b0000000000001010 '
1+
#1078
0+
#1079
b0000000000001011 '
1+
#1080
0+
#1081
b0000000000001100 '
1+
#1082
0+
#1083
b0000000000001101 '
1+
#1084
0+
#1085
b0000000000001110 '
1+
#1086
0+
#1087
b0000000000001111 '
1+
#1088
0+
#1089
b11 #
b0000000000000000 '
1+
#1090
0+
#1091
b0000000000000001 '
1+
#1092
0+
#1093
b0000000000000010 '
1+
#1094
0+
#1095
b0000000000000011 '
1+
#1096
0+
#1097
b0000000000000100 '
1+
#1098
0+
#1099
b0000000000000101 '
1+
#1100
0+
#1101
b0000000000000110 '
1+
#1102
0+
#1103
b0000000000000111 '
1+
#1104
0+
#1105
b0000000000001000 '
1+
#1106
0+
#1107
b0000000000001001 '
1+
#1108
0+
#1109
b0000000000001010 '
1+
#1110
0+
#1111
b0000000000001011 '
1+
#1112
0+
#1113
b0000000000001100 '
1+
#1114
0+
#1115
b0000000000001101 '
1+
#1116
0+
#1117
b0000000000001110 '
1+
#1118
0+
#1119
b0000000000001111 '
1+
#1120
0+
#1121
b00 #
1&
b0000000000000000 '
1+
1-
#1122
0+
#1123
b01 #
b000 $
0&
1+
0-
#1124
0+
#1125
b0000000000000001 '
1+
#1126
0+
#1127
b0000000000000010 '
1+
#1128
0+
#1129
b0000000000000011 '
1+
#1130
0+
#1131
b0000000000000100 '
1+
#1132
0+
#1133
b0000000000000101 '
1+
#1134
0+
#1135
b0000000000000110 '
1+
#1136
0+
#1137
b0000000000000111 '
1+
#1138
0+
#1139
b10 #
b0000000000000000 '
1+
#1140
0+
#1141
b0000000000000001 '
1+
#1142
0+
#1143
b0000000000000010 '
1+
#1144
0+
#1145
b0000000000000011 '
1+
#1146
0+
#1147
b0000000000000100 '
1+
#1148
0+
#1149
b0000000000000101 '
1+
#1150
0+
#1151
b0000000000000110 '
1+
#1152
0+
#1153
b0000000000000111 '
1+
#1154
0+
#1155
b0000000000001000 '
1+
#1156
0+
#1157
b0000000000001001 '
1+
#1158
0+
#1159
b0000000000001010 '
1+
#1160
0+
#1161
b0000000000001011 '
1+
#1162
0+
#1163
b0000000000001100 '
1+
#1164
0+
#1165
b0000000000001101 '
1+
#1166
0+
#1167
b0000000000001110 '
1+
#1168
0+
#1169
b0000000000001111 '
1+
#1170
0+
#1171
b001 $
b0000000000000000 '
1+
#1172
0+
#1173
b0000000000000001 '
1+
#1174
0+
#1175
b0000000000000010 '
1+
#1176
0+
#1177
b0000000000000011 '
1+
#1178
0+
#1179
b0000000000000100 '
1+
#1180
0+
#1181
b0000000000000101 '
1+
#1182
0+
#1183
b0000000000000110 '
1+
#1184
0+
#1185
b0000000000000111 '
1+
#1186
0+
#1187
b0000000000001000 '
1+
#1188
0+
#1189
b0000000000001001 '
1+
#1190
0+
#1191
b0000000000001010 '
1+
#1192
0+
#1193
b0000000000001011 '
1+
#1194
0+
#1195
b0000000000001100 '
1+
#1196
0+
#1197
b0000000000001101 '
1+
#1198
0+
#1199
b0000000000001110 '
1+
#1200
0+
#1201
b0000000000001111 '
1+
#1202
0+
#1203
b010 $
b0000000000000000 '
1+
#1204
0+
#1205
b0000000000000001 '
1+
#1206
0+
#1207
b0000000000000010 '
1+
#1208
0+
#1209
b0000000000000011 '
1+
#1210
0+
#1211
b0000000000000100 '
1+
#1212
0+
#1213
b0000000000000101 '
1+
#1214
0+
#1215
b0000000000000110 '
1+
#1216
0+
#1217
b0000000000000111 '
1+
#1218
0+
#1219
b0000000000001000 '
1+
#1220
0+
#1221
b0000000000001001 '
1+
#1222
0+
#1223
b0000000000001010 '
1+
#1224
0+
#1225
b0000000000001011 '
1+
#1226
0+
#1227
b0000000000001100 '
1+
#1228
0+
#1229
b0000000000001101 '
1+
#1230
0+
#1231
b0000000000001110 '
1+
#1232
0+
#1233
b0000000000001111 '
1+
#1234
0+
#1235
b011 $
b0000000000000000 '
1+
#1236
0+
#1237
b0000000000000001 '
1+
#1238
0+
#1239
b0000000000000010 '
1+
#1240
0+
#1241
b0000000000000011 '
1+
#1242
0+
#1243
b0000000000000100 '
1+
#1244
0+
#1245
b0000000000000101 '
1+
#1246
0+
#1247
b0000000000000110 '
1+
#1248
0+
#1249
b0000000000000111 '
1+
#1250
0+
#1251
b0000000000001000 '
1+
#1252
0+
#1253
b0000000000001001 '
1+
#1254
0+
#1255
b0000000000001010 '
1+
#1256
0+
#1257
b0000000000001011 '
1+
#1258
0+
#1259
b0000000000001100 '
1+
#1260
0+
#1261
b0000000000001101 '
1+
#1262
0+
#1263
b0000000000001110 '
1+
#1264
0+
#1265
b0000000000001111 '
1+
#1266
0+
#1267
b100 $
b0000000000000000 '
1+
#1268
0+
#1269
b0000000000000001 '
1+
#1270
0+
#1271
b0000000000000010 '
1+
#1272
0+
#1273
b0000000000000011 '
1+
#1274
0+
#1275
b0000000000000100 '
1+
#1276
0+
#1277
b0000000000000101 '
1+
#1278
0+
#1279
b0000000000000110 '
1+
#1280
0+
#1281
b0000000000000111 '
1+
#1282
0+
#1283
b0000000000001000 '
1+
#1284
0+
#1285
b0000000000001001 '
1+
#1286
0+
#1287
b0000000000001010 '
1+
#1288
0+
